README.rst
setup.py
gnm/__init__.py
gnm/gnm.py
gnm/quickstart.py
gnm/utils.py
gnm.egg-info/PKG-INFO
gnm.egg-info/SOURCES.txt
gnm.egg-info/dependency_links.txt
gnm.egg-info/requires.txt
gnm.egg-info/top_level.txt