Metadata-Version: 1.1
Name: gnm
Version: 1.0.2
Summary: Rock n Rolling awesome affine-invariant MCMC Sampler
Home-page: http://cims.nyu.edu/~mu388/gnm/
Author: Mehmet Ugurbil
Author-email: mu388@nyu.edu
License: MIT
Platform: UNKNOWN
Classifier: Development Status :: 5 - Production/Stable
Classifier: Intended Audience :: Developers
Classifier: Intended Audience :: Science/Research
Classifier: License :: OSI Approved :: MIT License
Classifier: Operating System :: OS Independent
Classifier: Programming Language :: Python :: 2.7
